hodor/__init__.py
hodorlive-1.2.17.dist-info/METADATA
hodorlive-1.2.17.dist-info/WHEEL
hodorlive-1.2.17.dist-info/licenses/LICENSE.md
hodorlive-1.2.17.dist-info/RECORD
