Metadata-Version: 2.4
Name: hodorlive
Version: 1.2.17
Summary: xpath/css based scraper with pagination
Project-URL: Homepage, https://github.com/CompileInc/hodor
Project-URL: Download, https://github.com/CompileInc/hodor/archive/v1.2.17.tar.gz
Author-email: Compile Inc <dev@compile.com>
License: MIT
License-File: LICENSE.md
Keywords: cssselect,hodor,lxml,scraping
Classifier: Intended Audience :: Developers
Classifier: Programming Language :: Python
Classifier: Programming Language :: Python :: 3.11
Requires-Python: >=3.11
Requires-Dist: cssselect==1.2.0
Requires-Dist: lxml>=4.9.1
Requires-Dist: reppy2==0.3.6
Requires-Dist: requests<2.40,>=2.32.3
